[
    {
        "hall_location": "hall 3 Stand A02",
        "company_name": "Bär GmbH\nHubarbeitsbühnen und Gerüstetechnik",
        "description": null
    },
    {
        "hall_location": "hall 3 Stand A03",
        "company_name": "AFS Airfilter Systeme GmbH",
        "description": "Machine extraction and good air conditions in your plant are essential for today's manufacturing processes. Central extraction systems or decentralized individu..."
    },
    {
        "hall_location": "hall 3 Stand A03",
        "company_name": "Hermann Bantleon GmbH",
        "description": null
    },
    {
        "hall_location": "hall 3 Stand A04/B05",
        "company_name": "IHG Spann- und Anwendungstechnik Vertriebs GmbH",
        "description": "System-Magnettechnik, Kleinmagnete, Magnethilfen, Lasthebemagnete..."
    },
    {
        "hall_location": "hall 3 Stand A04/B05",
        "company_name": "DADCO GmbH",
        "description": "Stickstoff-Gasdruckfedern..."
    },
    {
        "hall_location": "hall 3 Stand A04/B05",
        "company_name": "Ecoclean GmbH",
        "description": "Teilereinigungsanlagen auf Basis wässriger Medien, mit Kohlenwasserstoffen und alternativen Lösemitteln..."
    },
    {
        "hall_location": "hall 3 Stand A04/B05",
        "company_name": "indusa Industrielle Umweltschutzanlagen GmbH",
        "description": "Extraction systems for oil and emulsion mist, dust and odors. Electrostatic and mechanical filter systems, dust filter systems, wet scrubbers, filter fleece, fl..."
    },
    {
        "hall_location": "hall 3 Stand A04/B05",
        "company_name": "Diamant Weber AG",
        "description": "Diamant- und CBN-Werkzeuge..."
    },
    {
        "hall_location": "hall 3 Stand A04/B05",
        "company_name": "Berner + Straller GmbH",
        "description": "Normalien, Werkzeuge, Kühlschmierstoffe, Strahlanlagen, Werkzeugmaschinen..."
    },
    {
        "hall_location": "hall 3 Stand A04/B05",
        "company_name": "Agathon AG\nMaschinenfabrik",
        "description": "Stanz- und Formwerkzeuge, Normalien, Präzisionsführungselemente..."
    },
    {
        "hall_location": "hall 3 Stand A04/B05",
        "company_name": "IEPCO AG",
        "description": "Microstrahlanlagen, Polierstrahlanlagen, Strahlmittel und Zubehör; Tribologische Oberflächenbearbeitung..."
    },
    {
        "hall_location": "hall 3 Stand A04/B05",
        "company_name": "Maurer Magnetic AG",
        "description": "Messtechnik, Magnetismus..."
    },
    {
        "hall_location": "hall 3 Stand A04/B05",
        "company_name": "STOCKMEIER Chemie GmbH & Co. KG",
        "description": "Produkte auf wässriger- und Lösemittel-Basis zur industriellen Bauteilreinigung..."
    },
    {
        "hall_location": "hall 3 Stand A04/B05",
        "company_name": "Blaser Swisslube AG",
        "description": "Wassermischbare Kühlschmierstoffe und Metallbearbeitungsöle, Kühlmittelpflegegeräte..."
    },
    {
        "hall_location": "hall 3 Stand A07",
        "company_name": "WENDEL tools GmbH",
        "description": null
    },
    {
        "hall_location": "hall 3 Stand A07",
        "company_name": "EST Tools Austria GmbH",
        "description": null
    },
    {
        "hall_location": "hall 3 Stand A09",
        "company_name": "LSA | Automation",
        "description": null
    },
    {
        "hall_location": "hall 3 Stand A10",
        "company_name": "WEICON GmbH & Co. KG",
        "description": null
    },
    {
        "hall_location": "hall 3 Stand A12/B11",
        "company_name": "SPINNER\nWerkzeugmaschinenfabrik GmbH",
        "description": null
    },
    {
        "hall_location": "hall 3 Stand A18",
        "company_name": "Behringer GmbH",
        "description": null
    },
    {
        "hall_location": "hall 3 Stand A18",
        "company_name": "MAW Werkzeugmaschinen GmbH",
        "description": null
    },
    {
        "hall_location": "hall 3 Stand A18",
        "company_name": "Maschinenbau Silberhorn GmbH",
        "description": null
    },
    {
        "hall_location": "hall 3 Stand A18",
        "company_name": "Intermach Werkzeugmaschinen\nVertriebs-GmbH",
        "description": null
    },
    {
        "hall_location": "hall 3 Stand A18",
        "company_name": "Verband Deutscher Werkzeug- und\nFormenbauer e.V. (VDWF)",
        "description": null
    },
    {
        "hall_location": "hall 3 Stand A18",
        "company_name": "WM Mobilien Leasing GmbH",
        "description": null
    },
    {
        "hall_location": "hall 3 Stand A18",
        "company_name": "ebu Umformtechnik GmbH",
        "description": null
    },
    {
        "hall_location": "hall 3 Stand A18",
        "company_name": "TSCHUDIN AG",
        "description": null
    },
    {
        "hall_location": "hall 3 Stand A18",
        "company_name": "POLO Filter-Technik\nBremen GmbH",
        "description": null
    },
    {
        "hall_location": "hall 3 Stand A18",
        "company_name": "IAG TESTRÖ GmbH",
        "description": null
    },
    {
        "hall_location": "hall 3 Stand A18",
        "company_name": "exeron GmbH",
        "description": null
    },
    {
        "hall_location": "hall 3 Stand A20",
        "company_name": "MAVEG\nMaschinen-Vertriebs-Gesellschaft mbH",
        "description": null
    },
    {
        "hall_location": "hall 3 Stand A21",
        "company_name": "Arnold Werkzeugmaschinen\nGmbH & Co. KG",
        "description": null
    },
    {
        "hall_location": "hall 3 Stand A22",
        "company_name": "Albrecht Präzision GmbH & Co. KG",
        "description": "Wir führen Werkzeuge zu maximaler Leistung...."
    },
    {
        "hall_location": "hall 3 Stand A23",
        "company_name": "LISol Schmierstoffe GmbH",
        "description": null
    },
    {
        "hall_location": "hall 3 Stand A24",
        "company_name": "ZINNER GmbH\nPräzisionswerkzeuge",
        "description": null
    },
    {
        "hall_location": "hall 3 Stand A25",
        "company_name": "LiCoMo GmbH",
        "description": null
    },
    {
        "hall_location": "hall 3 Stand A26",
        "company_name": "Roboris-Deutschland GmbH",
        "description": null
    },
    {
        "hall_location": "hall 3 Stand A29",
        "company_name": "Röders GmbH",
        "description": null
    },
    {
        "hall_location": "hall 3 Stand A30",
        "company_name": "HWR Spanntechnik GmbH",
        "description": "We are Specialist in clamping deformation-sensitive workpieces of any shape..."
    },
    {
        "hall_location": "hall 3 Stand A31",
        "company_name": "RUF Maschinenbau GmbH & Co. KG",
        "description": "Hersteller von Brikettpressen für Metall-Späne,-Stäube,-Schlämme..."
    },
    {
        "hall_location": "hall 3 Stand A32",
        "company_name": "Taenzler Maschinen- und\nAnlagenbau GmbH",
        "description": "Manufacturer of conveyor systems/paternosters - in-house production for turned and milled parts...."
    },
    {
        "hall_location": "hall 3 Stand A37",
        "company_name": "Waldemar Loeser GmbH & Co. KG",
        "description": null
    },
    {
        "hall_location": "hall 3 Stand A37",
        "company_name": "Loeser GmbH",
        "description": null
    },
    {
        "hall_location": "hall 3 Stand A40",
        "company_name": "BÖHLER - voestalpine High Performance\nMetals Deutschland GmbH",
        "description": "Herstellung und Vertrieb von Werkzeug-, Pulvermetallurgischen- und Schnellarbeitsstählen, AM-Pulver, additiv gefertigte Bauteile sowie Wärmebehandlung, Oberfläc..."
    },
    {
        "hall_location": "hall 3 Stand A40",
        "company_name": "voestalpine eifeler Coating GmbH",
        "description": null
    },
    {
        "hall_location": "hall 3 Stand A41",
        "company_name": "Zeller & Gmelin GmbH & Co. KG",
        "description": null
    },
    {
        "hall_location": "hall 3 Stand A42",
        "company_name": "AIR LIQUIDE\nDeutschland GmbH",
        "description": null
    },
    {
        "hall_location": "hall 3 Stand A43",
        "company_name": "THIEL Storage & Handling Systems",
        "description": null
    },
    {
        "hall_location": "hall 3 Stand A44",
        "company_name": "Dormer Pramet\nZN der Sandvik Tooling\nDeutschland GmbH",
        "description": null
    },
    {
        "hall_location": "hall 3 Stand A44",
        "company_name": "Jurjanz GmbH & Co. KG",
        "description": "We have been supporting our customers in the field of custom, special and standard gauges as well as measuring equipment for more than 30 years. Our DIN EN ISO/..."
    },
    {
        "hall_location": "hall 3 Stand A46",
        "company_name": "Rump Strahlanlagen GmbH & Co. KG",
        "description": null
    },
    {
        "hall_location": "hall 3 Stand B01",
        "company_name": "Tresselt GmbH",
        "description": null
    },
    {
        "hall_location": "hall 3 Stand B03",
        "company_name": "Otto Dieterle Spezialwerkzeuge GmbH",
        "description": null
    },
    {
        "hall_location": "hall 3 Stand B04/C03",
        "company_name": "Maschinenfabrik Berthold HERMLE AG",
        "description": "HERMLE AG is a manufacturer of 3-, 4- and 5-axis machining centers and automation solutions...."
    },
    {
        "hall_location": "hall 3 Stand B08/C07",
        "company_name": "EMCO Deutschland GmbH",
        "description": "EMCO has been producing machine tools in Europe since 1947, offering solutions for several sectors...."
    },
    {
        "hall_location": "hall 3 Stand B09",
        "company_name": "A. Mannesmann\nMaschinenfabrik GmbH",
        "description": null
    },
    {
        "hall_location": "hall 3 Stand B09",
        "company_name": "Schneeberger GmbH",
        "description": "SCHNEEBERGER serves the world's most successful OEM customers with linear and profile guideways, gear racks and mineral casting\"..."
    },
    {
        "hall_location": "hall 3 Stand B12",
        "company_name": "Franken GmbH & Co. KG\nFabrik für Präzisionswerkzeuge",
        "description": "Fräswerkzeuge, Sonderfräser, Fräserspannmittel..."
    },
    {
        "hall_location": "hall 3 Stand B12",
        "company_name": "EMUGE - Werk Richard Glimpel\nGmbH & Co. KG",
        "description": "Gewindewerkzeuge, Bohrwerkzeuge, Gewindelehren, Spannzeuge..."
    },
    {
        "hall_location": "hall 3 Stand B19",
        "company_name": "EMAG Systems GmbH",
        "description": "EMAG Group – turning, drilling, milling, gear cutting, grinding, laser welding, joining, ECM...."
    },
    {
        "hall_location": "hall 3 Stand B20",
        "company_name": "GROB-WERKE GmbH & Co. KG",
        "description": "LIVE – 5-axis universal machining center G350 for unlimited possibilities in milling...."
    },
    {
        "hall_location": "hall 3 Stand B20",
        "company_name": "Ingersoll Werkzeuge GmbH",
        "description": "Ingersoll Cutting Tools is specialized in the production of cutting tools with an excellent vibration-free performance in both standard and special-purpose desi..."
    },
    {
        "hall_location": "hall 3 Stand B20",
        "company_name": "OPEN MIND Technologies AG",
        "description": null
    },
    {
        "hall_location": "hall 3 Stand B21",
        "company_name": "ITW e.V. Chemnitz\nInstitut für innovative Technologie",
        "description": null
    },
    {
        "hall_location": "hall 3 Stand B23",
        "company_name": "MAPAL\nFabrik für Präzisionswerkzeuge\nDr. Kress KG",
        "description": "MAPAL tools for the customer’s success MAPAL is one of the leading international suppliers of precision tools for the machining of practically all workpiece mat..."
    },
    {
        "hall_location": "hall 3 Stand B24/C25",
        "company_name": "Hwacheon Machinery Europe GmbH",
        "description": "Qualität aus Südkorea, Service aus Deutschland...."
    },
    {
        "hall_location": "hall 3 Stand B24/C25",
        "company_name": "HandlingTech Automations-Systeme\nGmbH",
        "description": null
    },
    {
        "hall_location": "hall 3 Stand B24/C25",
        "company_name": "Bodor Laser GmbH",
        "description": null
    },
    {
        "hall_location": "hall 3 Stand B24/C25",
        "company_name": "UNITECH-Maschinen GmbH",
        "description": "UNITECH ermöglicht als System- und Technologieintegrator eine flexible Produktion durch smarte Komplettlösungen für Zerspanung, Laserbearbeitung und Automatisie..."
    },
    {
        "hall_location": "hall 3 Stand B24/C25",
        "company_name": "ARO-tec GmbH",
        "description": null
    },
    {
        "hall_location": "hall 3 Stand B24/C25",
        "company_name": "Peter Lehmann AG",
        "description": null
    },
    {
        "hall_location": "hall 3 Stand B24/C25",
        "company_name": "unitech Kühlschmierstoffe GmbH",
        "description": null
    },
    {
        "hall_location": "hall 3 Stand B24/C25",
        "company_name": "PRIMINER Werkzeugmaschinen GmbH",
        "description": null
    },
    {
        "hall_location": "hall 3 Stand B25",
        "company_name": "Bolte GmbH, Bolzenschweißtechnik",
        "description": "Systemanbieter für Bolzenschweißtechnik. Alles aus einer Hand, für die perfekte Bolzenschweißverbindung!..."
    },
    {
        "hall_location": "hall 3 Stand B27",
        "company_name": "Okuma Deutschland GmbH",
        "description": "CNC Maschinen & CNC Steuerung www.okuma.de..."
    },
    {
        "hall_location": "hall 3 Stand B30/C31",
        "company_name": "SolidCAM GmbH",
        "description": "SolidCAM ist Marktführer im Bereich integrierter CAD/CAM-Systeme und bietet mit seinen Produkten SolidCAM und InventorCAM die nahtlose Integration in Solidworks..."
    },
    {
        "hall_location": "hall 3 Stand B30/C31",
        "company_name": "Solidcam Additive GmbH",
        "description": null
    },
    {
        "hall_location": "hall 3 Stand B31",
        "company_name": "Star Micronics GmbH",
        "description": null
    },
    {
        "hall_location": "hall 3 Stand B32",
        "company_name": "Lehmann GmbH\nPräzisionswerkzeuge",
        "description": "Entwicklung, Konstruktion, Herstellung und Service für Präzisionswerkzeuge zur spanenden und spanlosen Fertigung. Ausführung in VHM, PKD-, HM- oder Cermet-bestü..."
    },
    {
        "hall_location": "hall 3 Stand B33",
        "company_name": "Friedrich Britsch GmbH & Co. KG",
        "description": "With us, you get all the tools you need for the turned parts industy. everything. always. quick...."
    },
    {
        "hall_location": "hall 3 Stand B35",
        "company_name": "Willi Seiger GmbH",
        "description": null
    },
    {
        "hall_location": "hall 3 Stand B36",
        "company_name": "Ziersch GmbH",
        "description": null
    },
    {
        "hall_location": "hall 3 Stand B39",
        "company_name": "Dr. Matzat & Co. GmbH",
        "description": "Spanntechnik, Vorrichtungsbau, Normteile, Montagetechnik..."
    },
    {
        "hall_location": "hall 3 Stand B40",
        "company_name": "Vomat GmbH",
        "description": null
    },
    {
        "hall_location": "hall 3 Stand B41",
        "company_name": "Hufschmied\nZerspanungssysteme GmbH",
        "description": null
    },
    {
        "hall_location": "hall 3 Stand B43",
        "company_name": "oelheld GmbH",
        "description": null
    },
    {
        "hall_location": "hall 3 Stand B44",
        "company_name": "ELKA Schleif- und Poliermittel GmbH",
        "description": "We provide solutions for grinding,polishing/lapping, deburring and cleaning, standard and customized..."
    },
    {
        "hall_location": "hall 3 Stand B45",
        "company_name": "LTA Lufttechnik GmbH",
        "description": "Developing the future of filtration...."
    },
    {
        "hall_location": "hall 3 Stand B45",
        "company_name": "Armin Hamma Umwelttechnik",
        "description": "Armin Hamma Umwelttechnik – Your specialist for coolant technology and electronics...."
    },
    {
        "hall_location": "hall 3 Stand B45",
        "company_name": "Krug Werkzeugmaschinen\nInh. Jan Krug",
        "description": "LTA Filtrationssysteme für Öl- & Emulsionsnebel sowie Rauche & Stäube, SIEMENS Objektlöschanlagen für Werkzeugmaschinen, Armin Hamma Kühlschmierstofftechnik, Sp..."
    },
    {
        "hall_location": "hall 3 Stand B45",
        "company_name": "Siemens AG Österreich",
        "description": null
    },
    {
        "hall_location": "hall 3 Stand B46",
        "company_name": "TBH GmbH",
        "description": null
    },
    {
        "hall_location": "hall 3 Stand B47",
        "company_name": "Spanflug Technologies GmbH",
        "description": null
    },
    {
        "hall_location": "hall 3 Stand B49",
        "company_name": "Comprise IT Systeme GmbH",
        "description": null
    },
    {
        "hall_location": "hall 3 Stand B54",
        "company_name": "Formlabs GmbH",
        "description": "Formlabs is the professional 3D printer of choice for engineers, designers, healthcare providers, manufacturers, and decision-makers. Formlabs’ products include..."
    },
    {
        "hall_location": "hall 3 Stand B55",
        "company_name": "Schmuhl Faserverbundtechnik\nGmbH & Co. KG",
        "description": null
    },
    {
        "hall_location": "hall 3 Stand B55",
        "company_name": "Hightex\nVerstärkungsstrukturen GmbH",
        "description": null
    },
    {
        "hall_location": "hall 3 Stand B55",
        "company_name": "Leibniz - Institut für Polymerforschung Dresden e.V.",
        "description": null
    },
    {
        "hall_location": "hall 3 Stand B57",
        "company_name": "Quant Technik GmbH",
        "description": null
    },
    {
        "hall_location": "hall 3 Stand B58",
        "company_name": "AMbitious powered by toolcraft",
        "description": "toolcraft combines additive and subtractive technologies to manufacture precision parts and automation solutions. With AMbitious, we offer training and NX softw..."
    },
    {
        "hall_location": "hall 3 Stand B59",
        "company_name": "Röltgen GmbH und Co. KG",
        "description": null
    },
    {
        "hall_location": "hall 3 Stand B61",
        "company_name": "wefdi GmbH\nWerkzeuge für die Industrie",
        "description": null
    },
    {
        "hall_location": "hall 3 Stand B61",
        "company_name": "Accu-Lube Manufacturing GmbH",
        "description": null
    },
    {
        "hall_location": "hall 3 Stand B63",
        "company_name": "3D.aero GmbH",
        "description": null
    },
    {
        "hall_location": "hall 3 Stand C02",
        "company_name": "Gesau Technology GmbH",
        "description": "Entwicklung, Herstellung und Service von Präzisionswerkzeugen..."
    },
    {
        "hall_location": "hall 3 Stand C04/D05",
        "company_name": "INDEX-Werke GmbH & Co. KG\nHahn & Tessky",
        "description": "INDEX Werke zählt heute mit ihren Marken INDEX und TRAUB zu den weltweit führenden Herstellern von CNC-Drehmaschinen...."
    },
    {
        "hall_location": "hall 3 Stand C08/D07",
        "company_name": "BIKAR METALS",
        "description": "EVERYTHING with tradition..."
    },
    {
        "hall_location": "hall 3 Stand C11",
        "company_name": "Yamazaki Mazak Deutschland GmbH",
        "description": "Weltweit führend in der Herstellung modernster technischer Lösungen auf den Gebieten Multifunktions- und 5-Achs-Technologie, Fräsen, Drehen, CNC-Steuerung und A..."
    },
    {
        "hall_location": "hall 3 Stand C12",
        "company_name": "Willemin-Macodel SA",
        "description": "Our machines are the core of our solutions. They are the result of 50 years of experience in the machining of complex workpieces. They are precise, reliable and..."
    },
    {
        "hall_location": "hall 3 Stand C17",
        "company_name": "SMW-AUTOBLOK Spannsysteme GmbH",
        "description": null
    },
    {
        "hall_location": "hall 3 Stand C18",
        "company_name": "MTE Deutschland GmbH",
        "description": null
    },
    {
        "hall_location": "hall 3 Stand C26",
        "company_name": "IBERIMEX\nWerkzeugmaschinen GmbH",
        "description": "Seit über 50 Jahren bieten wir erstklassige Fräs- und Drehmaschinen für die Großteilbearbeitung. Von der Beratung über die Auswahl bis zur Inbetriebnahme und de..."
    },
    {
        "hall_location": "hall 3 Stand C32",
        "company_name": "Menzel Metallchemie GmbH",
        "description": "Minimum quantity lubrication/spray technology INDUTEC® MS process-reliable – cost-reducing – modular – flexible and environmentally friendly for your technologi..."
    },
    {
        "hall_location": "hall 3 Stand C33",
        "company_name": "BEOSYS GmbH",
        "description": null
    },
    {
        "hall_location": "hall 3 Stand C33",
        "company_name": "WSoptics GmbH",
        "description": null
    },
    {
        "hall_location": "hall 3 Stand C34",
        "company_name": "Lapmaster Wolters GmbH",
        "description": null
    },
    {
        "hall_location": "hall 3 Stand C36",
        "company_name": "Arnz Flott GmbH\nWerkzeugmaschinen",
        "description": null
    },
    {
        "hall_location": "hall 3 Stand C39",
        "company_name": "GNT Systems Germany GmbH",
        "description": null
    },
    {
        "hall_location": "hall 3 Stand C40",
        "company_name": "FREYLER Industriebau GmbH",
        "description": "Entdecken Sie zukunftsweisende Baukonzepte. FRELYER bietet Ihnen die Möglichkeit, maßgeschneiderte Bauprojekte zu realisieren, die speziell auf die Anforderunge..."
    },
    {
        "hall_location": "hall 3 Stand C40",
        "company_name": "Automationstechnik Schüller GmbH",
        "description": "Ihr Partner für Automationslösungen nach Maß: Engineering, Programmierung, Schaltschränke, Inbetriebnahme. Von der Komponente bis zur fertigen Automatisierung I..."
    },
    {
        "hall_location": "hall 3 Stand C40",
        "company_name": "SN-Spindeltechnik Steffen Nitschke",
        "description": "Spindle systems for robots, machine tools and test benches as well as repair, service and retrofitting..."
    },
    {
        "hall_location": "hall 3 Stand C40",
        "company_name": "DMG MORI Global Marketing GmbH",
        "description": "DMG MORI is a leading global manufacturer of high-precision machine tools. Technology integration, end-to-end automation and digitization solutions increase pro..."
    },
    {
        "hall_location": "hall 3 Stand C40",
        "company_name": "Botfellows GmbH",
        "description": null
    },
    {
        "hall_location": "hall 3 Stand C40",
        "company_name": "ROBUSTO\nMaschinen- und Metallbau\nHeiko May e.K.",
        "description": null
    },
    {
        "hall_location": "hall 3 Stand C40",
        "company_name": "ABG Marketing GmbH",
        "description": null
    },
    {
        "hall_location": "hall 3 Stand C40",
        "company_name": "TISORA\nSondermaschinen GmbH",
        "description": null
    },
    {
        "hall_location": "hall 3 Stand C40",
        "company_name": "Hiersemann\nProzessautomation GmbH",
        "description": null
    },
    {
        "hall_location": "hall 3 Stand C40",
        "company_name": "Stadt Chemnitz",
        "description": null
    },
    {
        "hall_location": "hall 3 Stand C40",
        "company_name": "ibs Automation GmbH",
        "description": "We develop and implement individually tailored, holistic, and ingenious systems and control solutions to provide our customers with a true competitive advantage..."
    },
    {
        "hall_location": "hall 3 Stand C40",
        "company_name": "Variomatic Werkzeugmaschinen GmbH",
        "description": null
    },
    {
        "hall_location": "hall 3 Stand C40",
        "company_name": "HZwo e.V.",
        "description": null
    },
    {
        "hall_location": "hall 3 Stand C40",
        "company_name": "Innovationsverbund Maschinenbau Sachsen VEMASinnovativ\nc/o Fraunhofer-Institut für Werkzeugmaschinen und Umformtechnik IWU",
        "description": "Technology and product-open network to support cross-industry exchange of knowledge and experience...."
    },
    {
        "hall_location": "hall 3 Stand C40",
        "company_name": "coreku\nGmbH & Co. KG",
        "description": null
    },
    {
        "hall_location": "hall 3 Stand C40",
        "company_name": "Mittelstand-Digital\nZentrum Chemnitz",
        "description": null
    },
    {
        "hall_location": "hall 3 Stand C40",
        "company_name": "Cobomatics",
        "description": null
    },
    {
        "hall_location": "hall 3 Stand C40",
        "company_name": "Hochschule für Technik und Wirtschaft Dresden (HTWD)\nUniversity of Applied Sciences",
        "description": null
    },
    {
        "hall_location": "hall 3 Stand C40",
        "company_name": "BEAS Technology GmbH",
        "description": null
    },
    {
        "hall_location": "hall 3 Stand C40",
        "company_name": "ICM - Institut Chemnitzer\nMaschinen- und Anlagenbau e.V.",
        "description": null
    },
    {
        "hall_location": "hall 3 Stand C40",
        "company_name": "Stahlbau Lüttewitz GmbH",
        "description": null
    },
    {
        "hall_location": "hall 3 Stand C40",
        "company_name": "Modellbau Clauß GmbH & Co. KG",
        "description": null
    },
    {
        "hall_location": "hall 3 Stand C40",
        "company_name": "Industrieverein\nSachsen 1828 e. V.",
        "description": null
    },
    {
        "hall_location": "hall 3 Stand C40",
        "company_name": "Siemens AG",
        "description": null
    },
    {
        "hall_location": "hall 3 Stand C40",
        "company_name": "Fraunhofer-Institut für Werkzeugmaschinen und Umformtechnik IWU",
        "description": null
    },
    {
        "hall_location": "hall 3 Stand C40",
        "company_name": "TU Chemnitz - Institut für Werkzeugmaschinen\nund Produktionsprozesse\nProfessur Produktionssysteme und -prozesse",
        "description": null
    },
    {
        "hall_location": "hall 3 Stand C40",
        "company_name": "VibroCut GmbH",
        "description": null
    },
    {
        "hall_location": "hall 3 Stand C41",
        "company_name": "Günter Effgen GmbH",
        "description": null
    },
    {
        "hall_location": "hall 3 Stand C43",
        "company_name": "Das Spindelwerk GmbH",
        "description": null
    },
    {
        "hall_location": "hall 3 Stand C43",
        "company_name": "MMD Werkzeugmaschinen-Vertrieb GmbH",
        "description": null
    },
    {
        "hall_location": "hall 3 Stand C47",
        "company_name": "DIRAK Dieter Ramsauer\nKonstruktionselemente GmbH",
        "description": "DIRAK GmbH impresses customers worldwide with pioneering solutions in mechanical and mechatronic locking, hinge and connection technology. Since 1991, the compa..."
    },
    {
        "hall_location": "hall 3 Stand C48",
        "company_name": "3D-Metall Theobald e.K.",
        "description": "3D-Metall ist Spezialist in der Produktion hochwertiger Metallteile (Stahl&Bronze) mittels Powder Bed Fusion. Wir fokussieren uns auf die additiven Fertigung vo..."
    },
    {
        "hall_location": "hall 3 Stand C48",
        "company_name": "Mark3D GmbH",
        "description": null
    },
    {
        "hall_location": "hall 3 Stand C48",
        "company_name": "Fraunhofer-Institut für Fertigungstechnik\nund Angewandte Materialforschung IFAM",
        "description": null
    },
    {
        "hall_location": "hall 3 Stand C48",
        "company_name": "Fraunhofer-Institut für\nWerkstoff- und Strahltechnik IWS",
        "description": null
    },
    {
        "hall_location": "hall 3 Stand C48",
        "company_name": "Sächsisches Textilforschungsinsitut e.V. (STFI)",
        "description": null
    },
    {
        "hall_location": "hall 3 Stand C48",
        "company_name": "Technologieforum Additive Fertigung",
        "description": null
    },
    {
        "hall_location": "hall 3 Stand C48",
        "company_name": "1A Technologies\nUG (haftungsbeschränkt)",
        "description": null
    },
    {
        "hall_location": "hall 3 Stand C49",
        "company_name": "Hovmand A/S",
        "description": null
    },
    {
        "hall_location": "hall 3 Stand C53",
        "company_name": "Heinz Soyer\nBolzenschweißtechnik GmbH",
        "description": null
    },
    {
        "hall_location": "hall 3 Stand C56",
        "company_name": "Bio-Circle Surface Technology GmbH",
        "description": null
    },
    {
        "hall_location": "hall 3 Stand C57",
        "company_name": "GO GERMAN\nPersonal aus Asien",
        "description": null
    },
    {
        "hall_location": "hall 3 Stand D01",
        "company_name": "Kurt Breuning\nIRCO Maschinenbau GmbH",
        "description": "Technik fürs Drehen Automatisch durch die Spindel beladen und entladen. Individuelle Beratung und die optimale Lösung für jede Anforderung sind Ausdruck unserer..."
    },
    {
        "hall_location": "hall 3 Stand D06/E05",
        "company_name": "SEW-EURODRIVE GmbH & Co. KG",
        "description": null
    },
    {
        "hall_location": "hall 3 Stand D08/E07",
        "company_name": "Citizen Machinery Europe GmbH",
        "description": "Mit Cincom und Miyano haben wir zwei weltweit führende CNC-Drehautomaten-Marken im Kurz- und Langdrehbereich im Programm. Zusätzlich bieten wir auch maßgeschnei..."
    },
    {
        "hall_location": "hall 3 Stand D28",
        "company_name": "CGTech Deutschland GmbH\nVericut",
        "description": "Vericut nutzt Ihre NC-Daten für mehr Sicherheit durch Simulation und mehr Effizienz durch Optimierung und entlastet so Ihr Personal entscheidend...."
    },
    {
        "hall_location": "hall 3 Stand D28",
        "company_name": "Cimatron Technologies GmbH",
        "description": "One CAM software to program all your machines - from simple lathes to complex, multi-channel turn-mill centers and Swiss Style machines...."
    },
    {
        "hall_location": "hall 3 Stand D28",
        "company_name": "TDM Systems GmbH",
        "description": null
    },
    {
        "hall_location": "hall 3 Stand D29",
        "company_name": "WFL Millturn Technologies\nGmbH & Co. KG",
        "description": null
    },
    {
        "hall_location": "hall 3 Stand D30",
        "company_name": "Laser Lounge GmbH",
        "description": null
    },
    {
        "hall_location": "hall 3 Stand D31",
        "company_name": "BIG DAISHOWA GmbH",
        "description": null
    },
    {
        "hall_location": "hall 3 Stand D32",
        "company_name": "Seco Tools GmbH",
        "description": null
    },
    {
        "hall_location": "hall 3 Stand D32",
        "company_name": "HK-Wütschner GmbH",
        "description": null
    },
    {
        "hall_location": "hall 3 Stand D32",
        "company_name": "EWS\nWeigele GmbH & Co. KG",
        "description": null
    },
    {
        "hall_location": "hall 3 Stand D32",
        "company_name": "Kennametal Deutschland GmbH",
        "description": null
    },
    {
        "hall_location": "hall 3 Stand D32",
        "company_name": "Sandvik Tooling Deutschland GmbH",
        "description": null
    },
    {
        "hall_location": "hall 3 Stand D32",
        "company_name": "Precitool Werkzeughandel\nGmbH + Co. KG",
        "description": null
    },
    {
        "hall_location": "hall 3 Stand D32",
        "company_name": "Hengst-Kessler GmbH",
        "description": null
    },
    {
        "hall_location": "hall 3 Stand D33",
        "company_name": "plato-tec GmbH",
        "description": null
    },
    {
        "hall_location": "hall 3 Stand D35",
        "company_name": "ProductionToGo GmbH",
        "description": null
    },
    {
        "hall_location": "hall 3 Stand D36",
        "company_name": "BAYKAL MAKINA SAN VE TC A.S",
        "description": null
    },
    {
        "hall_location": "hall 3 Stand D40",
        "company_name": "NRU GmbH",
        "description": null
    },
    {
        "hall_location": "hall 3 Stand D40",
        "company_name": "HTWK Hochschule für Technik,\nWirtschaft und Kultur Leipzig",
        "description": null
    },
    {
        "hall_location": "hall 3 Stand D40",
        "company_name": "ARC Solutions GmbH\nSiemens PLM Solution Partner",
        "description": null
    },
    {
        "hall_location": "hall 3 Stand D40",
        "company_name": "neo.NET e.V.",
        "description": null
    },
    {
        "hall_location": "hall 3 Stand D40",
        "company_name": "fertig+ GmbH",
        "description": null
    },
    {
        "hall_location": "hall 3 Stand D40",
        "company_name": "DP Solutions GmbH & Co. KG",
        "description": null
    },
    {
        "hall_location": "hall 3 Stand D40",
        "company_name": "KF Strahltechnik Dresden GmbH",
        "description": null
    },
    {
        "hall_location": "hall 3 Stand D40",
        "company_name": "ALOtec Dresden GmbH",
        "description": "Weltweit führend in der Technologie zum Laserhärten, Auftragschweißen und Additive Fertigung...."
    },
    {
        "hall_location": "hall 3 Stand D40",
        "company_name": "DICK & DICK Laserschneid- und\nSystemtechnik GmbH",
        "description": null
    },
    {
        "hall_location": "hall 3 Stand D40",
        "company_name": "Building 3D e.V.",
        "description": null
    },
    {
        "hall_location": "hall 3 Stand D40",
        "company_name": "Schweißtechnische Lehr- und\nVersuchsanstalt Halle GmbH",
        "description": null
    },
    {
        "hall_location": "hall 3 Stand D48",
        "company_name": "Fraunhofer Institut für\nWerkzeugmaschinen und\nUmformtechnik IWU",
        "description": null
    },
    {
        "hall_location": "hall 3 Stand D48",
        "company_name": "TU Chemnitz - Institut für\nWerkzeugmaschinen und\nProduktionsprozesse",
        "description": null
    },
    {
        "hall_location": "hall 3 Stand E01",
        "company_name": "Rapidobject GmbH",
        "description": null
    },
    {
        "hall_location": "hall 3 Stand E02",
        "company_name": "Butzbach Marking GmbH",
        "description": null
    },
    {
        "hall_location": "hall 3 Stand E03",
        "company_name": "Migatronic Schweißmaschinen GmbH",
        "description": null
    },
    {
        "hall_location": "hall 3 Stand E04/F03",
        "company_name": "CERATIZIT Deutschland GmbH",
        "description": "CERATIZIT has been a pioneer in the field of sophisticated hard material solutions for machining for over 100 years. Our extensive portfolio includes around 50,..."
    },
    {
        "hall_location": "hall 3 Stand E06",
        "company_name": "Stuhlmann Zerspanungstechnik GmbH",
        "description": null
    },
    {
        "hall_location": "hall 3 Stand E06",
        "company_name": "STB System Technik\nfür Betriebsmittel GmbH",
        "description": null
    },
    {
        "hall_location": "hall 3 Stand E06",
        "company_name": "Tungaloy-NTK Germany GmbH",
        "description": null
    },
    {
        "hall_location": "hall 3 Stand E08",
        "company_name": "SCHIESS\nWerkzeugmaschinenfabrik GmbH",
        "description": null
    },
    {
        "hall_location": "hall 3 Stand E10/F11",
        "company_name": "FRAISA GmbH",
        "description": "FRAISA produziert Hochleistungswerkzeuge für die Metallbearbeitung und zählt zu den führenden Herstellern der Zerspanungsbranche...."
    },
    {
        "hall_location": "hall 3 Stand E10/F11",
        "company_name": "Bilz Werkzeugfabrik GmbH & Co. KG",
        "description": null
    },
    {
        "hall_location": "hall 3 Stand E10/F11",
        "company_name": "VDMA e.V. Präzisionswerkzeuge",
        "description": null
    },
    {
        "hall_location": "hall 3 Stand E10/F11",
        "company_name": "VDMA e.V. Mess- und Prüftechnik",
        "description": null
    },
    {
        "hall_location": "hall 3 Stand E10/F11",
        "company_name": "Hobe GmbH",
        "description": "Die Hobe GmbH ist ein süddeutscher Hersteller von Präzisionswerkzeugen für die Innenformgebung kleinster Bohrungen im Durchmesserbereich Ø 0,3-8mm. Wir entwicke..."
    },
    {
        "hall_location": "hall 3 Stand E10/F11",
        "company_name": "Cimtrode GmbH",
        "description": null
    },
    {
        "hall_location": "hall 3 Stand E10/F11",
        "company_name": "DIATEST\nHermann Költgen GmbH",
        "description": null
    },
    {
        "hall_location": "hall 3 Stand E10/F11",
        "company_name": "ZECHA Hartmetall-Werkzeugfabrikation GmbH",
        "description": null
    },
    {
        "hall_location": "hall 3 Stand E10/F11",
        "company_name": "VDMA Services GmbH",
        "description": null
    },
    {
        "hall_location": "hall 3 Stand E11",
        "company_name": "Gühring KG",
        "description": null
    },
    {
        "hall_location": "hall 3 Stand E16",
        "company_name": "Maschinen Wagner\nWerkzeugmaschinen GmbH",
        "description": null
    },
    {
        "hall_location": "hall 3 Stand E17",
        "company_name": "Otto Roth GmbH & Co KG\nNiederlassung Chemnitz",
        "description": "Your reliable partner for standard, drawing, pipe connection parts, Kanban systems & e-business..."
    },
    {
        "hall_location": "hall 3 Stand E28",
        "company_name": "LANG Technik GmbH",
        "description": null
    },
    {
        "hall_location": "hall 3 Stand E31",
        "company_name": "Zhejiang Boesion PT Tech Co.,Ltd",
        "description": "Boesion is the manufacture for high precision nuts, like KMT KMTA ZM ZMV AM KM N TN and other high precision nuts. Besides locknuts, we also produce spherical w..."
    },
    {
        "hall_location": "hall 3 Stand E31",
        "company_name": "Keli Buff MFG. Co., Ltd",
        "description": null
    },
    {
        "hall_location": "hall 3 Stand E32",
        "company_name": "AVANTEC Zerspantechnik GmbH",
        "description": null
    },
    {
        "hall_location": "hall 3 Stand E34",
        "company_name": "AdeQuate Solutions GmbH",
        "description": "from incoming orders through production to the finished workpiece..."
    },
    {
        "hall_location": "hall 3 Stand F01",
        "company_name": "Kaindl\nSchleiftechnik Reiling GmbH",
        "description": null
    },
    {
        "hall_location": "hall 3 Stand F04/G03",
        "company_name": "TRUMPF\nSE + Co. KG",
        "description": null
    },
    {
        "hall_location": "hall 3 Stand F05",
        "company_name": "ACI Laser GmbH",
        "description": "ACI Laser develops, manufactures and sells laser systems for marking, engraving and laser trimming...."
    },
    {
        "hall_location": "hall 3 Stand F07",
        "company_name": "LISSMAC Maschinenbau GmbH",
        "description": "Deburring, edge rounding, surface finishing, slag and oxide layer removal with LISSMAC..."
    },
    {
        "hall_location": "hall 3 Stand F07",
        "company_name": "Kuhlmeyer Maschinenbau GmbH",
        "description": null
    },
    {
        "hall_location": "hall 3 Stand F07",
        "company_name": "Mende Industrieprodukte e.K.",
        "description": null
    },
    {
        "hall_location": "hall 3 Stand F08",
        "company_name": "REHM GmbH u.Co. KG\nSchweisstechnik",
        "description": null
    },
    {
        "hall_location": "hall 3 Stand F12/G11",
        "company_name": "Senfeng CNC Laser Germany GmbH",
        "description": null
    },
    {
        "hall_location": "hall 3 Stand F17",
        "company_name": "Mayr Antriebstechnik\nChr. Mayr GmbH + Co. KG",
        "description": null
    },
    {
        "hall_location": "hall 3 Stand F18",
        "company_name": "Blue LaserTools GmbH",
        "description": null
    },
    {
        "hall_location": "hall 3 Stand F18",
        "company_name": "Precitec GmbH & Co. KG",
        "description": null
    },
    {
        "hall_location": "hall 3 Stand F19",
        "company_name": "R. Stock AG\nPräzisionswerkzeuge",
        "description": null
    },
    {
        "hall_location": "hall 3 Stand G01",
        "company_name": "Bock Handelsunternehmen GmbH",
        "description": null
    },
    {
        "hall_location": "hall 3 Stand G04/H03",
        "company_name": "Ernst Graf GmbH",
        "description": null
    },
    {
        "hall_location": "hall 3 Stand G04/H03",
        "company_name": "Hartmetall Werkzeugfabrik\nPaul Horn GmbH",
        "description": null
    },
    {
        "hall_location": "hall 3 Stand G07",
        "company_name": "Ferdinand Gross GmbH & Co. KG",
        "description": null
    },
    {
        "hall_location": "hall 3 Stand G07",
        "company_name": "Nord-Lock GmbH",
        "description": null
    },
    {
        "hall_location": "hall 3 Stand G08",
        "company_name": "E. ZOLLER GmbH & Co. KG\nEinstell- und Messgeräte",
        "description": null
    },
    {
        "hall_location": "hall 3 Stand G12",
        "company_name": "ZCC Cutting Tools Europe GmbH",
        "description": "ZCC Cutting Tools Europe ist die EU-Niederlassung des größten chinesischen Hartmetallwerkzeugherstellers. Der Konzern produziert und vertreibt Lösungen für die..."
    },
    {
        "hall_location": "hall 3 Stand G12",
        "company_name": "Metrom Mechatronische\nMaschinen GmbH",
        "description": null
    },
    {
        "hall_location": "hall 3 Stand G18",
        "company_name": "Scaglia INDEVA GmbH",
        "description": "Scaglia INDEVA GmbH entwickelt und produziert Handhabungsgeräte und Greifer seit 1970 und nimmt heute eine führende Rolle bei der Handhabung von Lasten mittels..."
    },
    {
        "hall_location": "hall 3 Stand G19",
        "company_name": "ACSYS Lasertechnik GmbH",
        "description": "ACSYS is a leading supplier of high-precision standard and special laser machines...."
    },
    {
        "hall_location": "hall 3 Stand G23",
        "company_name": "Sandvik Tooling Deutschland GmbH",
        "description": null
    },
    {
        "hall_location": "hall 3 Stand G23",
        "company_name": "WTO Werkzeug-Einrichtungen GmbH",
        "description": null
    },
    {
        "hall_location": "hall 3 Stand G23",
        "company_name": "Dormer Pramet\nZN der Sandvik Tooling\nDeutschland GmbH",
        "description": null
    },
    {
        "hall_location": "hall 3 Stand G23",
        "company_name": "MAXION\nJänsch und Ortlepp GmbH",
        "description": null
    },
    {
        "hall_location": "hall 3 Stand G23",
        "company_name": "Eugen Fahrion GmbH & Co. KG",
        "description": null
    },
    {
        "hall_location": "hall 3 Stand G23",
        "company_name": "fruitcore robotics GmbH",
        "description": null
    },
    {
        "hall_location": "hall 3 Stand G23",
        "company_name": "Precitool Werkzeughandel\nGmbH + Co. KG",
        "description": null
    },
    {
        "hall_location": "hall 3 Stand G23",
        "company_name": "Thur Metall AG",
        "description": null
    },
    {
        "hall_location": "hall 3 Stand G23",
        "company_name": "HENKA Werkzeuge +\nWerkzeugmaschinen GmbH",
        "description": null
    },
    {
        "hall_location": "hall 3 Stand G24",
        "company_name": "LUKAS-ERZETT GmbH & Co. KG",
        "description": null
    },
    {
        "hall_location": "hall 3 Stand G31",
        "company_name": "BLM GROUP",
        "description": "BLM GROUP: tube and sheet metal laser cutting, cold saw, bending, end-forming...."
    },
    {
        "hall_location": "hall 3 Stand G33",
        "company_name": "OVEDO GmbH & Co. KG",
        "description": "Wer ist OVEDO? Wir sind ein Anbieter von Tiefbohrfrästechnik, Spannsystemen, Spänepressen, Spindelservice und Reparaturdienstleistungen. Im Fokus steht die Effi..."
    },
    {
        "hall_location": "hall 3 Stand H02",
        "company_name": "Emil Wirth Maschinenbau GmbH",
        "description": "Wir sind Ihr kompetenter und zuverlässiger Partner für Lohnfertigung in der industriellen Blechbearbeitung und Zerspanung. Von einfachen Stanz-Laserzuschnitten,..."
    },
    {
        "hall_location": "hall 3 Stand H04",
        "company_name": "BIMATEC SORALUCE\nZerspanungstechnologie GmbH",
        "description": "For over 30 years ...because it's the head that counts! Passion drives us: We develop groundbreaking technologies and find the best solutions...."
    },
    {
        "hall_location": "hall 3 Stand H07",
        "company_name": "Strödter Handhabungstechnik GmbH",
        "description": null
    },
    {
        "hall_location": "hall 3 Stand H08",
        "company_name": "HAHN+KOLB Werkzeuge GmbH",
        "description": "HAHN+KOLB ist eine global aufgestellte Gruppe in der Werkzeug­branche. Wir bieten unseren Kunden, technische Fachberatung, zahl­reiche Services und eine moderne..."
    },
    {
        "hall_location": "hall 3 Stand H12",
        "company_name": "SIMTEK\nPräzisionswerkzeuge GmbH",
        "description": "Tools for highest expectations: More than 11,000 standard and several thousand customized tools for groove turning, turning, circular milling, slotting, thread..."
    },
    {
        "hall_location": "hall 3 Stand H13",
        "company_name": "Vargus Deutschland GmbH",
        "description": "VARGUS is a leading global developer, manufacturer and supplier of high-quality precision tools for thread cutting, grooving, turning and manual deburring for t..."
    },
    {
        "hall_location": "hall 3 Stand H21",
        "company_name": "MICRO-EPSILON Optronic GmbH",
        "description": "Shaping the Future with Sensors...."
    },
    {
        "hall_location": "hall 3 Stand H22",
        "company_name": "ARNO Werkzeuge\nKarl-Heinz Arnold GmbH",
        "description": "Sie haben herausfordernde Zerspanungsaufgaben? Wir haben herausragende Lösungen! Bereits seit vier Generationen entwickeln wir Werkzeugsysteme, die durch Qualit..."
    },
    {
        "hall_location": "hall 3 Stand H23",
        "company_name": "NORIAN INC",
        "description": null
    },
    {
        "hall_location": "hall 3 Stand H25",
        "company_name": "Automation, Sonder- und Werkzeugmaschinen ASW GmbH",
        "description": "construction, machining, assembly of automation, special machinery, machine tools..."
    },
    {
        "hall_location": "hall 3 Stand H26",
        "company_name": "RAIS",
        "description": null
    },
    {
        "hall_location": "hall 3 Stand H26",
        "company_name": "deeg GmbH",
        "description": null
    },
    {
        "hall_location": "hall 3 Stand H26",
        "company_name": "ELMAG Entwicklungs und Handels GmbH",
        "description": null
    },
    {
        "hall_location": "hall 3 Stand H26",
        "company_name": "Piper GmbH Werkzeugmaschinen",
        "description": null
    },
    {
        "hall_location": "hall 3 Stand H27",
        "company_name": "Kreon Deutschland GmbH",
        "description": null
    },
    {
        "hall_location": "hall 3 Stand H30",
        "company_name": "Lianyungang Orientcraft Abrasives Co.Ltd",
        "description": null
    },
    {
        "hall_location": "hall 3 Stand H30/1",
        "company_name": "YingLong SuperHard Materials Manufactory",
        "description": null
    },
    {
        "hall_location": "hall 3 Stand H30/2",
        "company_name": "Guilin Hualun Diamond Tools Co.,Ltd",
        "description": null
    },
    {
        "hall_location": "hall 3 Stand H30/3",
        "company_name": "Henan Sanhui New Materials Co., Ltd",
        "description": null
    },
    {
        "hall_location": "hall 3 Stand H31",
        "company_name": "STILL GmbH\nHauptniederlassung Berlin",
        "description": null
    },
    {
        "hall_location": "hall 3 Stand I01",
        "company_name": "Neuhäuser Präzisionswerkzeuge GmbH",
        "description": null
    },
    {
        "hall_location": "hall 3 Stand I03",
        "company_name": "encee GmbH",
        "description": null
    },
    {
        "hall_location": "hall 3 Stand I04",
        "company_name": "ERBO GmbH",
        "description": "ERBO specialises in individual, customised solutions for extraction systems and intelligent chip handling in many different machining industries...."
    },
    {
        "hall_location": "hall 3 Stand I06",
        "company_name": "MOTUL Deutschland GmbH",
        "description": null
    },
    {
        "hall_location": "hall 3 Stand I07",
        "company_name": "CIDAN Machinery Germany GmbH",
        "description": "The CIDAN Group offers sheet metal processing companies innovative machine and software solutions...."
    },
    {
        "hall_location": "hall 3 Stand I09",
        "company_name": "WIKUS-Sägenfabrik\nWilhelm H. Kullmann\nGmbH & Co. KG",
        "description": "Precision at the Cutting Point: High-tech sawing tools for industry and trade since 1958..."
    },
    {
        "hall_location": "hall 3 Stand I10",
        "company_name": "Utilis AG",
        "description": null
    },
    {
        "hall_location": "hall 3 Stand I12",
        "company_name": "Liqui Moly GmbH",
        "description": null
    },
    {
        "hall_location": "hall 3 Stand I15",
        "company_name": "OPTOGON Industrielaser Manufaktur",
        "description": "Hersteller industrieller Laseranlagen für Beschriftung, Gravur, Reinigung und Strukturierung – mit automatisierten Lösungen für höchste Effizienz und skalierbar..."
    },
    {
        "hall_location": "hall 3 Stand I16",
        "company_name": "GEWATEC GmbH & Co. KG",
        "description": null
    },
    {
        "hall_location": "hall 3 Stand I20",
        "company_name": "Ronchini Massimo s.r.l.",
        "description": null
    },
    {
        "hall_location": "hall 3 Stand I21",
        "company_name": "Feinwerktechnik Göring\nGmbH & Co. KG",
        "description": "milled parts 2000 x 800 x 850 mm turned parts Ø 10 to Ø 1200 x 3500 mm up to 4 tons Gears Module 0.3 – 10, angle 15°, 20°, 30° from quantity one 1 to small seri..."
    },
    {
        "hall_location": "hall 3 Stand I21",
        "company_name": "Metalltechnik Göring GmbH",
        "description": "- Steel and metal construction -mechanical engineering -Max. component weight 5 tons -Conveyor technology, belt drums -industrial assembly -Sheet metal processi..."
    },
    {
        "hall_location": "hall 3 Stand I21",
        "company_name": "Arnstädter Verzahnungstechnik GmbH",
        "description": null
    },
    {
        "hall_location": "hall 3 Stand I21",
        "company_name": "Landesentwicklungsgesellschaft\nThüringen mbH",
        "description": null
    },
    {
        "hall_location": "hall 3 Stand I21",
        "company_name": "ifm electronic gmbh",
        "description": null
    },
    {
        "hall_location": "hall 3 Stand I21",
        "company_name": "FKT Formenbau und\nKunststofftechnik GmbH",
        "description": null
    },
    {
        "hall_location": "hall 3 Stand I27",
        "company_name": "Siegbert Kinne\nCNC-Werkzeugschleiferei",
        "description": null
    },
    {
        "hall_location": "hall 3 Stand I29",
        "company_name": "Shanghai Nagoya Precision Tools Co.,Ltd",
        "description": null
    },
    {
        "hall_location": "hall 3 Stand I31",
        "company_name": "Master Fluid Solutions WDG GmbH",
        "description": "Master Fluid Solutions bietet mit der Marke TRIM wassermischbare Hochleistungs-Kühlschmierstoffe für vielfältige Anwendungen, ergänzt durch Industrie- und Syste..."
    },
    {
        "hall_location": "hall 3 Stand A02",
        "company_name": "Bär GmbH\nHubarbeitsbühnen und Gerüstetechnik",
        "description": null
    },
    {
        "hall_location": "hall 3 Stand A03",
        "company_name": "AFS Airfilter Systeme GmbH",
        "description": "Machine extraction and good air conditions in your plant are essential for today's manufacturing processes. Central extraction systems or decentralized individu..."
    },
    {
        "hall_location": "hall 3 Stand A03",
        "company_name": "Hermann Bantleon GmbH",
        "description": null
    }
]